CHANGES.txt
LICENSE.txt
MANIFEST.in
README.rst
setup.cfg
setup.py
celerytestworker/__init__.py
celerytestworker/utils.py
celerytestworker/worker.py
celerytestworker.egg-info/PKG-INFO
celerytestworker.egg-info/SOURCES.txt
celerytestworker.egg-info/dependency_links.txt
celerytestworker.egg-info/requires.txt
celerytestworker.egg-info/top_level.txt