Metadata-Version: 1.1
Name: celerytestworker
Version: 0.0.4
Summary: Control (start/stop) a Celery standalone worker for running test purpose
Home-page: http://github.com/osantana/celerytestworker
Author: Osvaldo Santana Neto
Author-email: celerytestworker@osantana.me
License: MIT
Download-URL: https://github.com/osantana/celerytestworker/tarball/0.0.4
Keywords: testing test server
Platform: any
Classifier: Development Status :: 3 - Alpha
Classifier: Intended Audience :: Developers
Classifier: License :: OSI Approved :: MIT License
Classifier: Natural Language :: English
Classifier: Operating System :: OS Independent
Classifier: Topic :: Software Development :: Libraries
Classifier: Topic :: Software Development :: Testing
Classifier: Programming Language :: Python
Classifier: Programming Language :: Python :: 2
Classifier: Programming Language :: Python :: 2.7
Classifier: Programming Language :: Python :: 3
Classifier: Programming Language :: Python :: 3.4
